hl7v2json/__init__.py
hl7v2json/parser.py
hl7v2json/data/__init__.py
hl7v2json/data/27/__init__.py
hl7v2json/data/bamboo/__init__.py
hl7v2json/data/bamboo/fields.json
hl7v2json/data/bamboo/messages.json
hl7v2json/data/bamboo/segments.json
tests/__init__.py
tests/samples.py
tests/test_parser.py
hl7v2json-1.0.2.dist-info/LICENSE
hl7v2json-1.0.2.dist-info/METADATA
hl7v2json-1.0.2.dist-info/WHEEL
hl7v2json-1.0.2.dist-info/top_level.txt
hl7v2json-1.0.2.dist-info/RECORD
