Metadata-Version: 2.1
Name: hl7v2json
Version: 1.0.2
Summary: A simple library to convert HL7v2 to JSON
Home-page: https://github.com/kharoutaj/hl7v2json
Author: John Kharouta
Author-email: mjolnir117@gmail.com
License: UNKNOWN
Keywords: HL7,Health Level 7,healthcare,health care,medical record
Platform: UNKNOWN
Classifier: Programming Language :: Python :: 3
Classifier: License :: OSI Approved :: MIT License
Classifier: Operating System :: OS Independent
Requires-Python: >3.6
Requires-Dist: hl7 (==0.4.5)
Requires-Dist: six (==1.11.0)
